{"response":200,"data":{"id":360410,"name":"Maple Wood Floor Lamp: Clarity","cost":220,"comfort":60,"rank":3,"icon":"UI_Homeworld_Interior_Dq_Lamp_Lamp_03_Vo","route":"Maple Wood Floor Lamp: Clarity","categories":["Ornaments"],"types":["Lighting"],"description":"This large lamp can be found in the Yashiro Commission headquarters. It is quite pricey, and its creation process requires a lot of material and manpower.\\nIt is said that the Yashiro Commission once spent a large sum of money during a certain economically lean period to hire artisans to make a great number of products, such that these artisans might sustain their livelihoods. This special lamp was purchased during that period.","recipe":{"exp":60,"time":50400,"input":{"101310":{"icon":"UI_ItemIcon_101310","count":4},"101401":{"icon":"UI_ItemIcon_101401","count":4},"101403":{"icon":"UI_ItemIcon_101403","count":4}}},"tips":null}}