{"response":200,"data":{"id":361502,"name":"Teahouse Counter: \"Toshimaru\"","cost":85,"comfort":60,"rank":3,"icon":"UI_Homeworld_Interior_Dq_Table_Teahousetable_01_Vo","route":"Teahouse Counter: \"Toshimaru\"","categories":["Large Furnishing"],"types":["Counter"],"description":"A counter used in a teahouse that is made out of Maple Wood that has been painted in deep colors.\\nThis sort of counter has a secret room on the inside and storage space ample enough to hold fourteen dogs the size of Taroumaru, hence its nickname, \"Toshimaru.\"\\nThere seems to be no difference in the outer and inner face of the counter, and even the staff sometimes cannot tell which side is which.","recipe":{"exp":60,"time":50400,"input":{"101310":{"icon":"UI_ItemIcon_101310","count":12}}},"tips":null}}