{"response":200,"data":{"id":362303,"name":"Tavern Rug: Home Away From Home","cost":85,"comfort":60,"rank":3,"icon":"UI_Homeworld_Interior_Ly_Carpet_Carpet_04_Vo","route":"Tavern Rug: Home Away From Home","categories":["Small Furnishing"],"types":["Carpet"],"description":"A rug after the style of those found in Wangshu Inn. There are herbal components in the green dye used to make it that can not only eliminate excess moisture but that also smell uniquely good, leading to a warm and homely atmosphere for the guests.","recipe":{"exp":60,"time":50400,"input":{"101401":{"icon":"UI_ItemIcon_101401","count":8},"101403":{"icon":"UI_ItemIcon_101403","count":2},"101404":{"icon":"UI_ItemIcon_101404","count":2}}},"tips":null}}