{"response":200,"data":{"id":86,"name":"The Nation of Hydro's Mottled Colors","icon":"UI_Home_Suite_Exterior_Fd_Field_Vegetation","route":"The Nation of Hydro's Mottled Colors","categories":["Outdoor Set"],"types":["Gift Set"],"description":"A countryside scene full of luxurious plants. It contains all sorts of flowers and bushes that can be found everywhere in Fontaine. Flowers and plants are common themes in paintings, and are a starting point for explorations into \"color.\" Some painters in Fontaine believe that the world's palette uses plants to demonstrate the perfect combination of colors. As such, if all the colors in a painting may find their source in flowers, then this painting must surely have harmonious beauty equal to that of natural scenery. Of course, this is predicated on you not mixing all plant-derived colors together in a single conversation...","suiteItemList":{"360435":{"rank":3,"icon":"UI_Homeworld_Exterior_Fd_Lamp_Light_YwLudeng_01_Vo"},"370328":{"rank":3,"icon":"UI_Homeworld_Exterior_Fd_Decoration_Prop_HuaTanwei_01_Lod0"},"370815":{"rank":3,"icon":"UI_Homeworld_Exterior_Fd_Build_YwMinju_02_Lod0"},"371134":{"rank":3,"icon":"UI_Homeworld_Exterior_Fd_Build_YwShuita_01_Lod0"},"372344":{"rank":3,"icon":"UI_Homeworld_Exterior_Fd_Plant_Tree_ZhucBaishu_01_Lod0"},"372494":{"rank":3,"icon":"UI_Homeworld_Exterior_Fd_Plant_Grass_Fenlaba_01_Lod0"},"372495":{"rank":3,"icon":"UI_Homeworld_Exterior_Fd_Plant_Grass_ZiHuacong_01_Lod0"},"372496":{"rank":3,"icon":"UI_Homeworld_Exterior_Fd_Plant_Grass_Xiangrikui_01_Lod0"}},"favoriteNpcList":null}}